odoo/addons/account_edi_no_product_name_match/README.rst
odoo/addons/account_edi_no_product_name_match/__init__.py
odoo/addons/account_edi_no_product_name_match/__manifest__.py
odoo/addons/account_edi_no_product_name_match/i18n/account_edi_no_product_name_match.pot
odoo/addons/account_edi_no_product_name_match/i18n/it.po
odoo/addons/account_edi_no_product_name_match/models/__init__.py
odoo/addons/account_edi_no_product_name_match/models/account_edi_format.py
odoo/addons/account_edi_no_product_name_match/readme/CONTRIBUTORS.md
odoo/addons/account_edi_no_product_name_match/readme/DESCRIPTION.md
odoo/addons/account_edi_no_product_name_match/static/description/icon.png
odoo/addons/account_edi_no_product_name_match/static/description/index.html
odoo/addons/account_edi_no_product_name_match/tests/__init__.py
odoo/addons/account_edi_no_product_name_match/tests/test_account_edi_no_product_name_match.py
odoo_addon_account_edi_no_product_name_match-16.0.1.0.0.4.dist-info/METADATA
odoo_addon_account_edi_no_product_name_match-16.0.1.0.0.4.dist-info/WHEEL
odoo_addon_account_edi_no_product_name_match-16.0.1.0.0.4.dist-info/top_level.txt
odoo_addon_account_edi_no_product_name_match-16.0.1.0.0.4.dist-info/RECORD
