Metadata-Version: 2.1
Name: odoo-addon-account_edi_no_product_name_match
Version: 16.0.1.0.0.4
Summary: Disable product matching by name in Account EDI imports
Home-page: https://github.com/OCA/edi
Author: ACSONE SA/NV,Odoo Community Association (OCA)
Author-email: support@odoo-community.org
License: AGPL-3
Classifier: Programming Language :: Python
Classifier: Framework :: Odoo
Classifier: Framework :: Odoo :: 16.0
Classifier: License :: OSI Approved :: GNU Affero General Public License v3
Requires-Python: >=3.10
Requires-Dist: odoo<16.1dev,>=16.0a
